bskzephyr/__init__.py
bskzephyr/exceptions.py
bskzephyr/py.typed
bskzephyr-1.0.4.dist-info/METADATA
bskzephyr-1.0.4.dist-info/WHEEL
bskzephyr-1.0.4.dist-info/licenses/LICENSE
bskzephyr-1.0.4.dist-info/RECORD
