Metadata-Version: 2.4
Name: bskzephyr
Version: 1.0.4
Summary: Asynchronous library to control BSK Zephyr heat recovery devices using BSK Connect APIs.
Project-URL: Repository, https://github.com/andersonshatch/bskzephyr
Project-URL: Issues, https://github.com/andersonshatch/bskzephyr/issues
Author-email: Josh Anderson <andersonshatch@gmail.com>
License-Expression: MIT
License-File: LICENSE
Requires-Python: >=3.11
Requires-Dist: aiohttp
Requires-Dist: pydantic>=2.10.6
